docs/fw_gear/context.md
docs/fw_gear/getting_started.md
docs/fw_gear/reference.md
docs/fw_gear/release_notes.md
docs/fw_gear/specs.md
docs/fw_gear/utils.md
docs/fw_gear/migrate-guide/general_feature_parity.md
docs/fw_gear/migrate-guide/how_to_migrate.md
fw_gear/__init__.py
fw_gear/config.py
fw_gear/context.py
fw_gear/engine_metadata_schema.json
fw_gear/file.py
fw_gear/gear_spec_schema.json
fw_gear/invocation_schema.py
fw_gear/manifest.py
fw_gear/manifest.schema.json
fw_gear/metadata.py
fw_gear/logging/__init__.py
fw_gear/logging/defaults/debug.json
fw_gear/logging/defaults/info.json
fw_gear/utils/__init__.py
fw_gear/utils/contextutils.py
fw_gear/utils/sdk_helpers.py
fw_gear/utils/utils_helpers.py
fw_gear/utils/archive/__init__.py
fw_gear/utils/archive/zip_manager.py
fw_gear/utils/licenses/__init__.py
fw_gear/utils/licenses/freesurfer.py
fw_gear/utils/wrapper/__init__.py
fw_gear/utils/wrapper/command.py
fw_gear/utils/wrapper/nipype.py
fw_gear/utils/wrapper/hpc/__init__.py
fw_gear/utils/wrapper/hpc/freesurfer_utils.py
fw_gear/utils/wrapper/hpc/singularity.py
public/fw_gear/context/index.html
public/fw_gear/getting_started/index.html
public/fw_gear/migrate-guide/general_feature_parity/index.html
public/fw_gear/migrate-guide/how_to_migrate/index.html
public/fw_gear/reference/index.html
public/fw_gear/release_notes/index.html
public/fw_gear/specs/index.html
public/fw_gear/utils/index.html
fw_gear-0.3.5.dist-info/METADATA
fw_gear-0.3.5.dist-info/WHEEL
fw_gear-0.3.5.dist-info/entry_points.txt
fw_gear-0.3.5.dist-info/licenses/LICENSE
fw_gear-0.3.5.dist-info/RECORD
