Metadata-Version: 2.4
Name: fw-gear
Version: 0.3.5
Summary: Flywheel Gear Development Toolkit
Author-email: Flywheel <support@flywheel.io>
License-Expression: MIT
License-File: LICENSE
Requires-Python: ~=3.9
Requires-Dist: dotty-dict<2,>=1.3.1
Requires-Dist: fw-meta<5,>=4.2.2
Requires-Dist: jinja2==3.1.6
Requires-Dist: jsonschema<5,>=4.0.0
Provides-Extra: all
Requires-Dist: flywheel-sdk>=14.2.0; extra == 'all'
Requires-Dist: nipype<2,>=1.9.2; extra == 'all'
Requires-Dist: numpy<2,>=1; extra == 'all'
Requires-Dist: psutil<8,>=7.0.0; extra == 'all'
Provides-Extra: dicom
Provides-Extra: fw-file
Provides-Extra: monitoring
Requires-Dist: psutil<8,>=7.0.0; extra == 'monitoring'
Provides-Extra: nipype
Requires-Dist: nipype<2,>=1.9.2; extra == 'nipype'
Provides-Extra: numpy
Requires-Dist: numpy<2,>=1; extra == 'numpy'
Provides-Extra: sdk
Requires-Dist: flywheel-sdk>=14.2.0; extra == 'sdk'
